MANIFEST.in
readme.md
setup.py
django_shop_ceca.egg-info/PKG-INFO
django_shop_ceca.egg-info/SOURCES.txt
django_shop_ceca.egg-info/dependency_links.txt
django_shop_ceca.egg-info/requires.txt
django_shop_ceca.egg-info/top_level.txt
shop_ceca/__init__.py
shop_ceca/admin.py
shop_ceca/forms.py
shop_ceca/models.py
shop_ceca/offsite_ceca.py
shop_ceca/migrations/0001_initial.py
shop_ceca/migrations/__init__.py
shop_ceca/templates/shop_ceca/payment.html