Metadata-Version: 1.1
Name: django-shop-ceca
Version: 0.1.0
Summary: A pluggable Django application for integrating ceca tpv Payments
Home-page: http://github.com/josesanch/django-shop-ceca
Author: Jose Sanchez Moreno
Author-email: jose@o2w.es
License: UNKNOWN
Platform: UNKNOWN
Classifier: Development Status :: 3 - Alpha
Classifier: Environment :: Web Environment
Classifier: Framework :: Django
Classifier: Intended Audience :: Developers
Classifier: License :: OSI Approved :: BSD License
Classifier: Operating System :: OS Independent
Classifier: Programming Language :: Python
